CHANGELOG.md
CONTRIBUTING.md
LICENSE.md
MANIFEST.in
README.md
pyproject.toml
setup.cfg
setup.py
polarity_switcher/Daemon.py
polarity_switcher/Monitor.py
polarity_switcher/PolaritySwitcher.py
polarity_switcher/__init__.py
polarity_switcher/__main__.py
polarity_switcher/__project__.py
polarity_switcher/polarity_switcher.py
polarity_switcher.egg-info/PKG-INFO
polarity_switcher.egg-info/SOURCES.txt
polarity_switcher.egg-info/dependency_links.txt
polarity_switcher.egg-info/entry_points.txt
polarity_switcher.egg-info/requires.txt
polarity_switcher.egg-info/top_level.txt
polarity_switcher/conf/polaritySwitcher.ini
polarity_switcher/conf/polaritySwitcher_daemon.ini
polarity_switcher/conf/polaritySwitcher_database.ini
polarity_switcher/conf/polaritySwitcher_logging.ini