Metadata-Version: 2.1
Name: polarity-switcher
Version: 0.1.0
Summary: Readout software for the EPIC Polarity Switcher
Home-page: https://gitlab.ethz.ch/exotic-matter/cw-beam/polarity-switcher
Author: Carlos Vigo
Author-email: <carlosv@phys.ethz.ch>
License: GPLv3
Platform: UNKNOWN
Classifier: Programming Language :: Python :: 3.6
Classifier: License :: OSI Approved :: GNU General Public License v3 (GPLv3)
Classifier: Operating System :: POSIX :: Linux
Requires-Python: >=3.6
Provides-Extra: dev
Provides-Extra: docs
